moove/__init__.py
moove/app_state.py
moove/example_data/bird_x/experiment_a/day_1/batch.txt
moove/example_data/bird_x/experiment_a/day_1/bout_1.rec
moove/example_data/bird_x/experiment_a/day_1/bout_1.wav
moove/example_data/bird_x/experiment_a/day_1/bout_1.wav.not.mat
moove/example_data/white_noise/WN_40ms.wav
moove/models/CNN.py
moove/models/ConvMLP.py
moove/models/__init__.py
moove/moove_config.ini.example
moove/moovegui.py
moove/moovetaf.py
moove/templates/logo.png
moove/templates/logo_128.png
moove/templates/logo_128_white_bg_large.png
moove/templates/logo_128_white_bg_small.png
moove/templates/recfile_template.jinja
moove/utils/__init__.py
moove/utils/audio_utils.py
moove/utils/clustering_utils.py
moove/utils/dash_utils.py
moove/utils/file_utils.py
moove/utils/gui_utils.py
moove/utils/label_utils.py
moove/utils/movefuncs_utils.py
moove/utils/plot_utils.py
moove/utils/segment_utils.py
moove/utils/syllable_utils.py
moove/utils/training_utils.py
moove/utils/window_utils.py
moove-1.0.0.dist-info/LICENSE
moove-1.0.0.dist-info/METADATA
moove-1.0.0.dist-info/WHEEL
moove-1.0.0.dist-info/entry_points.txt
moove-1.0.0.dist-info/RECORD
