Metadata-Version: 2.3
Name: moove
Version: 1.0.0
Summary: A tool for real-time syllable segmentation and classification of birdsong, designed to enable closed-loop experiments in vocal learning research.
License: MIT
Author: Nils Riekers
Requires-Python: >=3.9,<3.13
Classifier: License :: OSI Approved :: MIT License
Classifier: Programming Language :: Python :: 3
Classifier: Programming Language :: Python :: 3.9
Classifier: Programming Language :: Python :: 3.10
Classifier: Programming Language :: Python :: 3.11
Classifier: Programming Language :: Python :: 3.12
Requires-Dist: dash (>=2.17.1)
Requires-Dist: evfuncs (>=0.3.5.post1)
Requires-Dist: jinja2 (>=3.1.4)
Requires-Dist: matplotlib (>=3.9.0)
Requires-Dist: numpy (>=1.26.4)
Requires-Dist: pandas (>=2.2.2)
Requires-Dist: pillow (>=10.0.0)
Requires-Dist: pyaudio (>=0.2.14)
Requires-Dist: rangeslider (>=2023.7.2)
Requires-Dist: scikit-learn (>=1.5.1)
Requires-Dist: seaborn (>=0.13.2)
Requires-Dist: sounddevice (>=0.5.0)
Requires-Dist: torch (>=2.0.0,<=2.5.0)
Requires-Dist: ttkbootstrap (>=1.10.1)
Requires-Dist: ttkwidgets (>=0.13.0)
Requires-Dist: umap-learn (>=0.5.6)
